setup.cfg
setup.py
pueuey/__init__.py
pueuey/conn_adapter.py
pueuey/log.py
pueuey/queue.py
pueuey/setup.py
pueuey/worker.py
pueuey.egg-info/PKG-INFO
pueuey.egg-info/SOURCES.txt
pueuey.egg-info/dependency_links.txt
pueuey.egg-info/not-zip-safe
pueuey.egg-info/requires.txt
pueuey.egg-info/top_level.txt
pueuey/sql/create_table.sql
pueuey/sql/ddl.sql
pueuey/sql/drop_ddl.sql