Metadata-Version: 1.1
Name: pueuey
Version: 1.0.post2
Summary: queue_classic ported to Python 2: Simple, efficient worker queue for Ruby & PostgreSQL.
Home-page: https://github.com/cecton/pueuey
Author: Cecile Tonglet
Author-email: cecile.tonglet@gmail.com
License: MIT
Keywords: postgres queue worker ruby
Platform: UNKNOWN
Classifier: Development Status :: 5 - Production/Stable
Classifier: Topic :: Database
Classifier: Topic :: System :: Distributed Computing
Classifier: License :: OSI Approved :: MIT License
